onegov.gis-0.9.2-py3.6-nspkg.pth
onegov/gis/.gitignore
onegov/gis/__init__.py
onegov/gis/integration.py
onegov/gis/upgrade.py
onegov/gis/assets/css/leaflet-control-geocoder.css
onegov/gis/assets/css/leaflet-easybutton.css
onegov/gis/assets/css/leaflet-integration.css
onegov/gis/assets/css/leaflet.css
onegov/gis/assets/css/images/geocoder.png
onegov/gis/assets/css/images/layers-2x.png
onegov/gis/assets/css/images/layers.png
onegov/gis/assets/css/images/marker-icon-2x.png
onegov/gis/assets/css/images/marker-icon.png
onegov/gis/assets/css/images/marker-shadow.png
onegov/gis/assets/js/geo-vermessungsamt-winterthur.js
onegov/gis/assets/js/geo-zugmap-luftbild.js
onegov/gis/assets/js/geo-zugmap-ortsplan.js
onegov/gis/assets/js/geo-zugmap.js
onegov/gis/assets/js/leaflet-control-geocoder.js
onegov/gis/assets/js/leaflet-easybutton.js
onegov/gis/assets/js/leaflet-integration.js
onegov/gis/assets/js/leaflet-sleep.js
onegov/gis/assets/js/leaflet.js
onegov/gis/assets/js/proj4js-leaflet.js
onegov/gis/assets/js/proj4js.js
onegov/gis/forms/__init__.py
onegov/gis/forms/fields.py
onegov/gis/forms/widgets.py
onegov/gis/models/__init__.py
onegov/gis/models/coordinates.py
onegov/gis/tests/conftest.py
onegov/gis/tests/test_fields.py
onegov/gis/tests/test_integration.py
onegov/gis/tests/test_models.py
onegov.gis-0.9.2.dist-info/METADATA
onegov.gis-0.9.2.dist-info/WHEEL
onegov.gis-0.9.2.dist-info/entry_points.txt
onegov.gis-0.9.2.dist-info/namespace_packages.txt
onegov.gis-0.9.2.dist-info/top_level.txt
onegov.gis-0.9.2.dist-info/RECORD
